adit_dicomweb_client/__init__.py
adit_dicomweb_client/adit_dicomweb_client.py
adit_dicomweb_client-0.1.1.dist-info/METADATA
adit_dicomweb_client-0.1.1.dist-info/WHEEL
adit_dicomweb_client-0.1.1.dist-info/RECORD
