Metadata-Version: 2.1
Name: adit-dicomweb-client
Version: 0.1.1
Summary: 
Author: Hummerich, Sander
Author-email: sander.hummerich@med.uni-heidelberg.de
Requires-Python: >=3.11,<4.0
Classifier: Programming Language :: Python :: 3
Classifier: Programming Language :: Python :: 3.11
Requires-Dist: dicomweb-client (>=0.59.1,<0.60.0)
Requires-Dist: pydicom (>=2.4.1,<3.0.0)
